analysis/__init__.py
analysis/agent_analysis.py
analysis/interface.py
analysis/security_analysis.py
analysis/utils.py
analysis/metrics/__init__.py
analysis/metrics/dashboard.py
analysis/metrics/llm_analytics.py
analysis/metrics/security_metrics.py
analysis/metrics/token_metrics.py
analysis/metrics/tool_metrics.py
api/__init__.py
api/middleware/__init__.py
api/middleware/error_handler.py
api/routes/__init__.py
api/routes/agents.py
api/routes/alert_metrics.py
api/routes/events.py
api/routes/health.py
api/routes/metrics.py
api/routes/security.py
api/routes/telemetry.py
api/schemas/__init__.py
api/schemas/agents.py
api/schemas/event.py
api/schemas/metrics.py
api/schemas/security.py
api/schemas/telemetry.py
config/__init__.py
config/processing_config.py
config/settings.py
cylestio_local_server/__init__.py
cylestio_local_server/cli.py
cylestio_local_server/server.py
cylestio_local_server/src.py
cylestio_local_server-0.1.20.dist-info/licenses/LICENSE
database/__init__.py
database/schema_design.md
database/schema_migration.py
database/session.py
models/__init__.py
models/agent.py
models/base.py
models/event.py
models/framework_event.py
models/llm_interaction.py
models/security_alert.py
models/session.py
models/span.py
models/tool_interaction.py
models/trace.py
processing/__init__.py
processing/simple_processor.py
services/__init__.py
services/conversation_service.py
services/pricing_service.py
services/security_event_processor.py
services/security_query.py
utils/__init__.py
utils/error_handling.py
utils/json_serializer.py
utils/logging.py
cylestio_local_server-0.1.20.dist-info/METADATA
cylestio_local_server-0.1.20.dist-info/WHEEL
cylestio_local_server-0.1.20.dist-info/entry_points.txt
cylestio_local_server-0.1.20.dist-info/top_level.txt
cylestio_local_server-0.1.20.dist-info/RECORD
