Metadata-Version: 2.4
Name: cylestio-local-server
Version: 0.1.20
Summary: A lightweight, self-hosted server for collecting, processing, and analyzing telemetry data from AI agents
Author-email: Cylestio Team <info@cylestio.com>
License:                                  Apache License
Project-URL: Homepage, https://github.com/cylestio/cylestio-local-server
Project-URL: Bug Tracker, https://github.com/cylestio/cylestio-local-server/issues
Project-URL: Documentation, https://github.com/cylestio/cylestio-local-server#readme
Keywords: ai,telemetry,monitoring,agents,llm
Classifier: Programming Language :: Python :: 3
Classifier: Programming Language :: Python :: 3.9
Classifier: Programming Language :: Python :: 3.10
Classifier: Programming Language :: Python :: 3.11
Classifier: License :: OSI Approved :: MIT License
Classifier: Operating System :: OS Independent
Classifier: Intended Audience :: Developers
Classifier: Topic :: Software Development :: Libraries :: Python Modules
Classifier: Topic :: System :: Monitoring
Requires-Python: >=3.9
License-File: LICENSE
Requires-Dist: fastapi>=0.109.2
Requires-Dist: uvicorn>=0.27.0
Requires-Dist: pydantic>=2.5.3
Requires-Dist: starlette>=0.40.0
Requires-Dist: python-multipart>=0.0.7
Requires-Dist: sqlalchemy>=2.0.25
Requires-Dist: alembic>=1.13.1
Requires-Dist: pandas>=2.1.4
Requires-Dist: numpy>=1.26.3
Requires-Dist: python-dotenv>=1.0.0
Requires-Dist: pyyaml>=6.0.1
Requires-Dist: dynaconf>=3.2.4
Requires-Dist: pydantic-settings>=2.0.0
Provides-Extra: dev
Requires-Dist: pytest>=7.4.4; extra == "dev"
Requires-Dist: httpx>=0.26.0; extra == "dev"
Requires-Dist: pytest-cov>=4.1.0; extra == "dev"
Requires-Dist: mypy>=1.8.0; extra == "dev"
Requires-Dist: typing-extensions>=4.9.0; extra == "dev"
Requires-Dist: requests>=2.31.0; extra == "dev"
Requires-Dist: psutil>=5.9.0; extra == "dev"
Dynamic: license-file
